<?xml version="1.0" encoding="UTF-8"?>
<!DOCTYPE bikeSharingFacilities SYSTEM "bikesharingfacilitiesE_v1.dtd">

<bikeSharingFacilities>

<bikeSharingFacility linkId="9991a" id="e_1bs_pt" x="498.958654" y="2322.657692" numberOfAvailableBikes="4" totalNumberOfBikeSlots="8" numberOfEmptyBikeParkings="4" type="e" cyclesInStation="e1_1,e1_2,e1_3,e1_4"/>
<bikeSharingFacility linkId="9992a" id="e_2bs" x="2243.574038" y="2322.657692" numberOfAvailableBikes="5" totalNumberOfBikeSlots="8" numberOfEmptyBikeParkings="3" type="e" cyclesInStation="e2_1,e2_2,e2_3,e2_4,e2_5"/>
<bikeSharingFacility linkId="9993a" id="e_3bs" x="2575.881731" y="2005.926923" numberOfAvailableBikes="3" totalNumberOfBikeSlots="8" numberOfEmptyBikeParkings="5" type="e" cyclesInStation="e3_1,e3_2,e3_3"/>
<bikeSharingFacility linkId="9994a" id="e_4bs_pt" x="2553.492538" y="1001.507012" numberOfAvailableBikes="4" totalNumberOfBikeSlots="8" numberOfEmptyBikeParkings="4" type="e" cyclesInStation="e4_1,e4_2,e4_3,e4_4"/>
<bikeSharingFacility linkId="9995a" id="e_5bs" x="2570.689423" y="245.734615" numberOfAvailableBikes="4" totalNumberOfBikeSlots="8" numberOfEmptyBikeParkings="4" type="e" cyclesInStation="e5_1,e5_2,e5_3,e5_4"/>
<bikeSharingFacility linkId="9996a" id="e_6bs" x="2466.843269" y="48.426923" numberOfAvailableBikes="4" totalNumberOfBikeSlots="8" numberOfEmptyBikeParkings="4" type="e" cyclesInStation="e6_1,e6_2,e6_3,e6_4"/>
<bikeSharingFacility linkId="9997a" id="e_7bs" x="1506.266346" y="-39.842308" numberOfAvailableBikes="5" totalNumberOfBikeSlots="8" numberOfEmptyBikeParkings="3" type="e" cyclesInStation="e7_1,e7_2,e7_3,e7_4,e7_5"/>
<bikeSharingFacility linkId="9998a" id="e_8bs" x="1241.458654" y="-45.034615" numberOfAvailableBikes="4" totalNumberOfBikeSlots="8" numberOfEmptyBikeParkings="4" type="e" cyclesInStation="e8_1,e8_2,e8_3,e8_4"/>
<bikeSharingFacility linkId="9999a" id="e_9bs" x="504.150962" y="-50.226923" numberOfAvailableBikes="3" totalNumberOfBikeSlots="8" numberOfEmptyBikeParkings="5" type="e" cyclesInStation="e9_1,e9_2,e9_3"/>
<bikeSharingFacility linkId="99910a" id="e_10bs" x="187.420192" y="250.926923" numberOfAvailableBikes="4" totalNumberOfBikeSlots="8" numberOfEmptyBikeParkings="4" type="e" cyclesInStation="e10_1,e10_2,e10_3,e10_4"/>
<bikeSharingFacility linkId="10006a" id="e_106bs" x="1542.6125" y="962.273077" numberOfAvailableBikes="4" totalNumberOfBikeSlots="8" numberOfEmptyBikeParkings="4" type="e" cyclesInStation="e106_1,e106_2,e106_3,e106_4"/>
<bikeSharingFacility linkId="10004a" id="e_104bs" x="1542.6125" y="1310.157692" numberOfAvailableBikes="4" totalNumberOfBikeSlots="8" numberOfEmptyBikeParkings="4" type="e" cyclesInStation="e104_1,e104_2,e104_3,e104_4"/>
<bikeSharingFacility linkId="10003a" id="e_103bs" x="1210.304808" y="1304.965385" numberOfAvailableBikes="4" totalNumberOfBikeSlots="8" numberOfEmptyBikeParkings="4" type="e" cyclesInStation="e103_1,e103_2,e103_3,e103_4"/>
<bikeSharingFacility linkId="10005a" id="e_105bs" x="1205.1125" y="957.080769" numberOfAvailableBikes="5" totalNumberOfBikeSlots="8" numberOfEmptyBikeParkings="3" type="e" cyclesInStation="e105_1,e105_2,e105_3,e105_4,e105_5"/>
<bikeSharingFacility linkId="10002a" id="e_11bs_pt" x="452.227885" y="1310.157692" numberOfAvailableBikes="4" totalNumberOfBikeSlots="6" numberOfEmptyBikeParkings="4" type="e" cyclesInStation="e11_1,e11_2,e11_3,e11_4"/>
<bikeSharingFacility linkId="10001a" id="e_12bs" x="187.420192" y="2005.926923" numberOfAvailableBikes="3" totalNumberOfBikeSlots="8" numberOfEmptyBikeParkings="5" type="e" cyclesInStation="e12_1,e12_2,e12_3"/>
<bikeSharingFacility linkId="99910a" id="e_17bs_pt" x="1545.528603" y="2055.606272" numberOfAvailableBikes="4" totalNumberOfBikeSlots="8" numberOfEmptyBikeParkings="4" type="e" cyclesInStation="e17_1,e17_2,e17_3,e17_4"/>
<bikeSharingFacility linkId="9991a" id="c1" x="500" y="2320" numberOfAvailableBikes="5" totalNumberOfBikeSlots="10" numberOfEmptyBikeParkings="5" type="c" cyclesInStation="c11,c12,c13,c14,c15"/>
<bikeSharingFacility linkId="9993a" id="c2pt" x="2575" y="2005" numberOfAvailableBikes="5" totalNumberOfBikeSlots="10" numberOfEmptyBikeParkings="5" type="c" cyclesInStation="c12,c22,c23,c24,c25"/>
<bikeSharingFacility linkId="10002a" id="c3pt" x="450" y="1310" numberOfAvailableBikes="5" totalNumberOfBikeSlots="10" numberOfEmptyBikeParkings="5" type="c" cyclesInStation="c31,c32,c33,c34,c35"/>
</bikeSharingFacilities>
